tensor_truth-0.1.15.dist-info/licenses/LICENSE
tensortruth/__init__.py
tensortruth/app.py
tensortruth/build_db.py
tensortruth/cli.py
tensortruth/cli_paths.py
tensortruth/fetch_sources.py
tensortruth/pdf_handler.py
tensortruth/preset_defaults.py
tensortruth/rag_engine.py
tensortruth/session_index.py
tensortruth/app_utils/__init__.py
tensortruth/app_utils/app_state.py
tensortruth/app_utils/chat_handler.py
tensortruth/app_utils/chat_utils.py
tensortruth/app_utils/commands.py
tensortruth/app_utils/config.py
tensortruth/app_utils/config_schema.py
tensortruth/app_utils/dialog_manager.py
tensortruth/app_utils/dialogs.py
tensortruth/app_utils/helpers.py
tensortruth/app_utils/logging_config.py
tensortruth/app_utils/paths.py
tensortruth/app_utils/pdf_ui.py
tensortruth/app_utils/presets.py
tensortruth/app_utils/presets_ui.py
tensortruth/app_utils/rendering.py
tensortruth/app_utils/session.py
tensortruth/app_utils/setup_state.py
tensortruth/app_utils/streaming.py
tensortruth/app_utils/title_generation.py
tensortruth/app_utils/vram.py
tensortruth/app_utils/modes/__init__.py
tensortruth/app_utils/modes/chat_mode.py
tensortruth/app_utils/modes/setup_mode.py
tensortruth/core/__init__.py
tensortruth/core/ollama.py
tensortruth/core/system.py
tensortruth/core/types.py
tensortruth/indexing/__init__.py
tensortruth/indexing/builder.py
tensortruth/media/app_styles.css
tensortruth/media/tensor_truth_banner.png
tensortruth/media/tensor_truth_icon_256.png
tensortruth/scrapers/__init__.py
tensortruth/scrapers/arxiv.py
tensortruth/scrapers/book.py
tensortruth/scrapers/common.py
tensortruth/scrapers/doxygen.py
tensortruth/scrapers/library.py
tensortruth/scrapers/sphinx.py
tensortruth/utils/__init__.py
tensortruth/utils/chat.py
tensortruth/utils/detection.py
tensortruth/utils/interactive.py
tensortruth/utils/metadata.py
tensortruth/utils/pdf.py
tensortruth/utils/sources_config.py
tensortruth/utils/validation.py
tensor_truth-0.1.15.dist-info/METADATA
tensor_truth-0.1.15.dist-info/WHEEL
tensor_truth-0.1.15.dist-info/entry_points.txt
tensor_truth-0.1.15.dist-info/top_level.txt
tensor_truth-0.1.15.dist-info/RECORD
