Metadata-Version: 2.4
Name: tensor-truth
Version: 0.1.15
Summary: Local RAG pipeline for fixing LLM hallucinations using high-precision documentation indexing.
Author-email: Relja Ljubobratovic <ljubobratovic.relja@gmail.com>
License: MIT
Keywords: rag,deepseek,ollama,pytorch,llm,local-ai
Requires-Python: >=3.11
License-File: LICENSE
Requires-Dist: transformers<4.47.0,>=4.40.0
Requires-Dist: tokenizers<0.21.0,>=0.19.0
Requires-Dist: huggingface-hub[hf_xet,inference]<1.0.0,>=0.23.0
Requires-Dist: sentence-transformers>=3.0.0
Requires-Dist: llama_parse<0.6.55,>=0.5.0
Requires-Dist: llama_cloud_services<0.6.55,>=0.6.0
Requires-Dist: llama-index>=0.10.0
Requires-Dist: llama-index-core
Requires-Dist: llama-index-llms-ollama
Requires-Dist: llama-index-embeddings-huggingface
Requires-Dist: llama-index-vector-stores-chroma
Requires-Dist: llama-index-readers-file
Requires-Dist: chromadb>=1.3.5
Requires-Dist: torch>=2.9
Requires-Dist: psutil
Requires-Dist: streamlit
Requires-Dist: requests
Requires-Dist: aiohttp
Requires-Dist: pymupdf-layout
Requires-Dist: pymupdf4llm
Requires-Dist: marker-pdf
Requires-Dist: tqdm
Provides-Extra: docs
Requires-Dist: beautifulsoup4; extra == "docs"
Requires-Dist: markdownify; extra == "docs"
Requires-Dist: sphobjinv; extra == "docs"
Requires-Dist: arxiv; extra == "docs"
Provides-Extra: dev
Requires-Dist: tensor-truth[docs]; extra == "dev"
Requires-Dist: pytest>=9.0.2; extra == "dev"
Requires-Dist: pytest-cov>=7.0.0; extra == "dev"
Requires-Dist: hypothesis>=6.82.0; extra == "dev"
Requires-Dist: black>=25.12.0; extra == "dev"
Requires-Dist: isort>=7.0.0; extra == "dev"
Requires-Dist: flake8>=7.3.0; extra == "dev"
Requires-Dist: mypy>=1.4.0; extra == "dev"
Requires-Dist: coverage[toml]>=7.2.0; extra == "dev"
Dynamic: license-file
